examples/sdk_test.py
trubrics/__init__.py
trubrics/config.py
trubrics/enums.py
trubrics/logger.py
trubrics/main.py
trubrics-1.8.4.dist-info/METADATA
trubrics-1.8.4.dist-info/WHEEL
trubrics-1.8.4.dist-info/top_level.txt
trubrics-1.8.4.dist-info/RECORD
