Metadata-Version: 2.2
Name: trubrics
Version: 1.8.4
Summary: Python SDK to track events in Trubrics.
Author-email: Jeff Kayne <jeff.kayne@trubrics.com>
License: Apache 2.0
Classifier: Programming Language :: Python :: 3
Classifier: Operating System :: OS Independent
Classifier: License :: OSI Approved :: Apache Software License
Requires-Python: >=3.10
Requires-Dist: requests>=2.31.0
